{
	"$schema": "https://raw.githubusercontent.com/xen-42/outer-wilds-new-horizons/main/NewHorizons/Schemas/body_schema.json",
	"name": "Ringed Giant",
	"starSystem": "AnonymousStrangerOW.StrangerSystem",
	"AmbientLights": [
		{
			"innerRadius": 800,
			"outerRadius": 850,
			"intensity": 2,
			"position": {
				"x": 0,
				"y": 0,
				"z": 0
			},
			"tint": {
				"r": 9,
				"g": 99,
				"b": 96,
				"a": 128
			}
		}
	],
	"Atmosphere": {
		"clouds": {
			"texturePath": "assets/Texture/ringedgiant.png",
			"capPath": "assets/Texture/ringedgiant_cap.png",
			"rampPath": "assets/Texture/ringedgiant_ramp.png",
			"outerCloudRadius": 800,
			"innerCloudRadius": 750,
			"fluidType": "water",
			"tint": {
				"r": 25,
				"g": 226,
				"b": 252
			}
		},
		"hasRain": true,
		"size": 800,
		"atmosphereTint": {
			"r": 25,
			"g": 226,
			"b": 252,
			"a": 140
		},
		"fogSize": 800,
		"fogTint": {
			"r": 25,
			"g": 226,
			"b": 252,
			"a": 20
		}
	},
	"Base": {
		"surfaceGravity": 20,
		"surfaceSize": 300
	},
	"HeightMap": {
		"redTile": {
			"textureTile": "assets/Texture/peacock-ore.png",
			"normalTile": "assets/Texture/peacock-ore_n.png",
			"smoothnessTile": "assets/Texture/peacock-ore_h.png",
			"size": 20
		},
		"tileBlendMap": "assets/Texture/dbm_r.png",
		"minHeight": 200,
		"maxHeight": 205
	},
	"MapMarker": {
		"enabled": true
	},
	"Water": {
		"size": 297,
		"density": 35,
		"tint": {
			"r": 9,
			"g": 99,
			"b": 96,
			"a": 128
		}
	},
	"Props": {
		"details": [
			{
				"assetBundle": "assets/AssetBundle/strangerbundle",
				"path": "Assets/RINGEDGIANT_ISLAND.prefab",
				"position": {
					"x": -46.6806,
					"y": -556.4532,
					"z": 53.9709
				},
				"rotation": {
					"x": 11.4527,
					"y": 150.9479,
					"z": 177.7284
				}
			},
			{
				"assetBundle": "assets/AssetBundle/strangerbundle",
				"path": "Assets/RINGEDGIANT_ISLAND2.prefab",
				"position": {
					"x": 46.6806,
					"y": 306.4532,
					"z": -53.9709
				}
			},
			{
				"path": "Sector_BH/Sector_Crossroads/Interactables_Crossroads/VisibleFrom_BH/Prefab_HEA_Campfire",
				"parentPath": "Sector/RINGEDGIANT_ISLAND2/Interactibles/NormalFire_Stranger",
				"isRelativeToParent": true,
				"removeChildren": [
					"Effects",
					"Props_HEA_Campfire"
				]
			},
			{
				"assetBundle": "assets/AssetBundle/strangerbundle",
				"path": "Assets/EYE/GhostBirdNPCs/Prefab_IP_GhostBird_ScientistDescendant_Vessel1.prefab",
				"parentPath": "Sector/Vessel_Body",
				"position": {
					"x": -901.0897,
					"y": 396.4904,
					"z": 909.8854
				},
				"rotation": {
					"x": 354.624,
					"y": 43.46161,
					"z": 335.0878
				}
			},
			{
				"assetBundle": "assets/AssetBundle/strangerbundle",
				"path": "Assets/Seals/Seal_Ringed.prefab",
				"position": {
					"x": -2.2376,
					"y": 338.9471,
					"z": -58.4961
				},
				"rotation": {
					"x": 354.6553,
					"y": 114.1547,
					"z": 0.1999
				}
			},
			{
				"path": "Sector/SpaceCenter/Props/GhostShip_COL (1)",
				"position": {
					"x": -53.8125,
					"y": -330.3578,
					"z": -5.4514
				},
				"rotation": {
					"x": 2.3036,
					"y": 74.5762,
					"z": 174.5877
				}
			},
			{
				"assetBundle": "assets/AssetBundle/strangerbundle",
				"path": "Assets/RaftDocks/RaftDock_Crimson.prefab",
				"rename": "RaftDock_Ringed_Device",
				"position": {
					"x": -181.9657,
					"y": -296.4325,
					"z": 12.2164
				},
				"rotation": {
					"x": 337.0275,
					"y": 278.4284,
					"z": 182.9359
				}
			},
			{
				"assetBundle": "assets/AssetBundle/strangerbundle",
				"path": "Assets/RaftDocks/RaftDock_Crimson.prefab",
				"rename": "RaftDock_Ringed_Camp",
				"position": {
					"x": 108.5648,
					"y": 331.9881,
					"z": -13.3222
				},
				"rotation": {
					"x": 13.096,
					"y": 77.2503,
					"z": 2.1199
				}
			}
		],
		"rafts": [
			{
				"rename": "RING_RAFT",
				"position": {
					"x": -192.1502,
					"y": -281.4666,
					"z": 13.4393
				},
				"alignRadial": true
			}
		],
		"entryLocation": [
			{
				"id": "RING",
				"cloaked": false
			},
			{
				"id": "RING_CAMP",
				"cloaked": false,
				"parentPath": "Sector/RINGEDGIANT_ISLAND2/Interactibles/NormalFire_Stranger",
				"isRelativeToParent": true
			},
			{
				"id": "RING_TRAVELER",
				"cloaked": false,
				"parentPath": "Sector/RINGEDGIANT_ISLAND/GhostBirdNPCs/Prefab_IP_GhostBird_Ringed/",
				"isRelativeToParent": true
			},
			{
				"id": "RING_SEAL",
				"cloaked": false,
				"parentPath": "Sector/Seal_Ringed",
				"isRelativeToParent": true
			},
			{
				"id": "RING_STRUCTURE",
				"cloaked": false,
				"parentPath": "Sector/RINGEDGIANT_ISLAND/Building/Base",
				"isRelativeToParent": true
			}
		],
		"dialogue": [
			{
				"xmlFile": "dialogue/NewTravelers/Ringed.xml",
				"parentPath": "Sector/RINGEDGIANT_ISLAND/GhostBirdNPCs/Prefab_IP_GhostBird_Ringed",
				"isRelativeToParent": true,
				"position": {
					"y": 3
				}
			},
			{
				"xmlFile": "dialogue/Homeworld/GhostNPC/DescendantVessel.xml",
				"parentPath": "Sector/Prefab_IP_GhostBird_ScientistDescendant_Vessel1",
				"isRelativeToParent": true,
				"position": {
					"y": 3
				}
			}
		],
		"signals": [
			{
				"frequency": "Strange Frequency",
				"name": "Bush's Signal",
				"audio": "assets/Audio/POSTLUDE_SIGNAL.ogg",
				"detectionRadius": 650,
				"identificationRadius": 20,
				"parentPath": "Sector/RINGEDGIANT_ISLAND/GhostBirdNPCs/Prefab_IP_GhostBird_Ringed",
				"isRelativeToParent": true,
				"position": {
					"y": 2
				}
			},
			{
				"frequency": "Unnerving Fluctuations",
				"name": "Ringed Giant Seal",
				"audio": "OW No-Eye Ruins 121120_2 AP LP",
				"detectionRadius": 300,
				"identificationRadius": 10,
				"parentPath": "Sector/Seal_Ringed",
				"isRelativeToParent": true,
				"position": {
					"y": 2
				}
			}
		]
	},
	"Orbit": {
		"semiMajorAxis": 13000,
		"isTidallyLocked": true,
		"alignmentAxis": {
			"x": 4,
			"y": -0.2,
			"z": 0
		},
		"primaryBody": "Nearest Neighbor",
		"tint": {
			"r": 4,
			"g": 249,
			"b": 249
		}
	},
	"Volumes": {
		"visorEffects": {
			"rainEffectVolumes": [
				{
					"radius": 750
				}
			]
		},
		"oxygenVolumes": [
			{
				"parentPath": "Sector/RINGEDGIANT_ISLAND2/Interactibles/OxygenVolumeSocket",
				"isRelativeToParent": true,
				"radius": 30
			}
		],
		"audioVolumes": [
			{
				"volume": 0.5,
				"priority": 1,
				"audio": "assets/Audio/terraformhome2.ogg",
				"track": "music",
				"parentPath": "Sector/RINGEDGIANT_ISLAND/Building/Base",
				"isRelativeToParent": true,
				"radius": 30
			},
			{
				"audio": "OW Finally Set Free 072021_2 AP",
				"parentPath": "Sector/RING_RAFT",
				"isRelativeToParent": true,
				"track": "music",
				"loop": true,
				"priority": 1,
				"radius": 3,
				"position": {
					"y": 2
				},
				"volume": 0.4
			},
			{
				"priority": 1,
				"audio": "OW Final End Times 022519_2 AP LOOP2",
				"track": "endTimesMusic",
				"parentPath": "Sector/Vessel_Body",
				"isRelativeToParent": true,
				"volume": 0.2,
				"radius": 99999,
				"rename": "FinalEndTimes_STR"
			}
		],
		"revealVolumes": [
			{
				"revealFor": "player",
				"revealOn": "enter",
				"radius": 750,
				"reveals": [ "RING_MAIN_E" ]
			},
			{
				"revealFor": "player",
				"revealOn": "enter",
				"radius": 20,
				"parentPath": "Sector/RINGEDGIANT_ISLAND/Building/Base",
				"isRelativeToParent": true,
				"reveals": [
					"RING_STRUCTURE_E",
					"RING_SEAL_R",
					"DESERT_SEAL_R",
					"CRIMSON_SEAL_R",
					"VOLCANO_SEAL_R",
					"QUANTUM_SEAL_R"
				]
			},
			{
				"revealFor": "player",
				"revealOn": "enter",
				"radius": 20,
				"parentPath": "Sector/RINGEDGIANT_ISLAND/Interactibles/SealSockets/Desert/Socket/Active",
				"isRelativeToParent": false,
				"position": {
					"x": -54.2699,
					"y": -321.8221,
					"z": 48.8352
				},
				"reveals": [
					"DESERT_SEAL_INSERT"
				]
			},
			{
				"revealFor": "player",
				"revealOn": "enter",
				"radius": 20,
				"parentPath": "Sector/RINGEDGIANT_ISLAND/Interactibles/SealSockets/Ringed/Socket/Active",
				"isRelativeToParent": false,
				"position": {
					"x": -54.2699,
					"y": -321.8221,
					"z": 48.8352
				},
				"reveals": [
					"RING_SEAL_INSERT"
				]
			},
			{
				"revealFor": "player",
				"revealOn": "enter",
				"radius": 20,
				"parentPath": "Sector/RINGEDGIANT_ISLAND/Interactibles/SealSockets/Crimson/Socket/Active",
				"isRelativeToParent": false,
				"position": {
					"x": -54.2699,
					"y": -321.8221,
					"z": 48.8352
				},
				"reveals": [
					"CRIMSON_SEAL_INSERT"
				]
			},
			{
				"revealFor": "player",
				"revealOn": "enter",
				"radius": 20,
				"parentPath": "Sector/RINGEDGIANT_ISLAND/Interactibles/SealSockets/CrimsonMoon/Socket/Active",
				"isRelativeToParent": false,
				"position": {
					"x": -54.2699,
					"y": -321.8221,
					"z": 48.8352
				},
				"reveals": [
					"VOLCANO_SEAL_INSERT"
				]
			},
			{
				"revealFor": "player",
				"revealOn": "enter",
				"radius": 20,
				"parentPath": "Sector/RINGEDGIANT_ISLAND/Interactibles/SealSockets/Enigma/Socket/Active",
				"isRelativeToParent": false,
				"position": {
					"x": -54.2699,
					"y": -321.8221,
					"z": 48.8352
				},
				"reveals": [
					"QUANTUM_SEAL_INSERT"
				]
			},
			{
				"revealFor": "player",
				"revealOn": "enter",
				"radius": 50,
				"parentPath": "Sector/Vessel_Body",
				"isRelativeToParent": true,
				"rename": "VESSEL_REVEAL",
				"reveals": [
					"HOME_VESSEL"
				]
			},
			{
				"revealFor": "player",
				"revealOn": "enter",
				"radius": 5,
				"parentPath": "Sector/Seal_Ringed",
				"isRelativeToParent": true,
				"reveals": [ "RING_SEAL_E" ]
			},
			{
				"revealFor": "player",
				"revealOn": "enter",
				"radius": 30,
				"parentPath": "Sector/RINGEDGIANT_ISLAND2/Interactibles/OxygenVolumeSocket",
				"isRelativeToParent": true,
				"reveals": [ "RING_CAMP_E" ]
			}
		]
	},
	"Rings": [
		{
			"unlit": true,
			"fluidType": "cloud",
			"texture": "assets/Texture/rings-home.png",
			"innerRadius": 0,
			"outerRadius": 2000
		}
	],
	"canShowOnTitle": false,
	"ShipLog": {
		"xmlFile": "shiplogs/ringedgiant.xml",
		"spriteFolder": "assets/Texture/Shiplog",
		"mapMode": {
			"revealedSprite": "assets/Texture/Shiplog/RINGEDGIANT_UI.png",
			"outlineSprite": "assets/Texture/Shiplog/RINGEDGIANT_UI_O.png",
			"scale": 5,
			"manualPosition": {
				"x": 800,
				"y": 0
			},
			"manualNavigationPosition": {
				"x": 2,
				"y": 0
			}
		}
	},
	"ParticleFields": [
		{
			"type": "clouds",
			"densityByHeightCurve": [
				{
					"density": 0,
					"height": 750
				},
				{
					"density": 50,
					"height": 749
				},
				{
					"density": 5,
					"height": 0
				}
			]
		},
		{
			"type": "bubbles",
			"densityByHeightCurve": [
				{
					"density": 20,
					"height": 297
				},
				{
					"density": 0,
					"height": 750
				}
			]
		}
	]
}